ethereumapis/__init__.py
ethereumapis/_internal/__init__.py
ethereumapis/_internal/github/__init__.py
ethereumapis/_internal/github/com/__init__.py
ethereumapis/_internal/github/com/gogo/__init__.py
ethereumapis/_internal/github/com/gogo/protobuf/__init__.py
ethereumapis/_internal/github/com/gogo/protobuf/gogoproto/__init__.py
ethereumapis/_internal/github/com/gogo/protobuf/gogoproto/gogo_pb2.py
ethereumapis/_internal/google/__init__.py
ethereumapis/_internal/google/api/__init__.py
ethereumapis/_internal/google/api/annotations_pb2.py
ethereumapis/_internal/google/api/http_pb2.py
ethereumapis/v1/__init__.py
ethereumapis/v1/attestation_pb2.py
ethereumapis/v1/beacon_block_pb2.py
ethereumapis/v1/beacon_chain_service_pb2.py
ethereumapis/v1/beacon_chain_service_pb2_grpc.py
ethereumapis/v1/beacon_debug_service_pb2.py
ethereumapis/v1/beacon_debug_service_pb2_grpc.py
ethereumapis/v1/beacon_state_pb2.py
ethereumapis/v1/node_pb2.py
ethereumapis/v1/node_pb2_grpc.py
ethereumapis/v1/validator_pb2.py
ethereumapis/v1/validator_service_pb2.py
ethereumapis/v1/validator_service_pb2_grpc.py
ethereumapis/v1alpha1/__init__.py
ethereumapis/v1alpha1/attestation_pb2.py
ethereumapis/v1alpha1/beacon_block_pb2.py
ethereumapis/v1alpha1/beacon_chain_pb2.py
ethereumapis/v1alpha1/beacon_chain_pb2_grpc.py
ethereumapis/v1alpha1/node_pb2.py
ethereumapis/v1alpha1/node_pb2_grpc.py
ethereumapis/v1alpha1/validator_pb2.py
ethereumapis/v1alpha1/validator_pb2_grpc.py
ethereumapis-0.12.0.dist-info/METADATA
ethereumapis-0.12.0.dist-info/RECORD
ethereumapis-0.12.0.dist-info/WHEEL
ethereumapis-0.12.0.dist-info/top_level.txt
