Metadata-Version: 2.1
Name: ethereumapis
Version: 0.12.0
Summary: Prysm's service interface definitions for the Ethereum 2.0 API
Home-page: https://github.com/prysmaticlabs/ethereumapis
Author: Prysmatic Labs
Author-email: contact@prysmaticlabs.com
Maintainer: wbn
Maintainer-email: wbn@striated.space
License: Apache License 2.0
Platform: any
Classifier: License :: OSI Approved :: Apache Software License
Requires-Python: >=3.5.0
Requires-Dist: grpcio (>=1.34.0)
Requires-Dist: protobuf (>=3.14.0)
